report_of_monaco_race_shinumerde/__init__.py
report_of_monaco_race_shinumerde/app/__init__.py
report_of_monaco_race_shinumerde/app/report.py
report_of_monaco_race_shinumerde/race_data/__init__.py
report_of_monaco_race_shinumerde/race_data/abbreviations.txt
report_of_monaco_race_shinumerde/race_data/end.log
report_of_monaco_race_shinumerde/race_data/start.log
report_of_monaco_race_shinumerde-2024.2.22.dist-info/METADATA
report_of_monaco_race_shinumerde-2024.2.22.dist-info/WHEEL
report_of_monaco_race_shinumerde-2024.2.22.dist-info/licenses/LICENSE
report_of_monaco_race_shinumerde-2024.2.22.dist-info/RECORD
