Metadata-Version: 2.1
Name: report_of_monaco_race_shinumerde
Version: 2024.2.22
Summary: A package for task 6
Project-URL: Homepage, https://github.com/pypa/sampleproject
Project-URL: Issues, https://github.com/pypa/sampleproject/issues
Author-email: Ruslan Vlasenko <shinumerde@gmail.com>
License-File: LICENSE
Classifier: License :: OSI Approved :: MIT License
Classifier: Operating System :: OS Independent
Classifier: Programming Language :: Python :: 3
Requires-Python: >=3.11
